{
  "name": "hyper3xpl0iter-gnutls",
  "version": "0.1.5",
  "author": "Andre Mattie",
  "summary": "Module for creating TLS certs and keys with GnuTLS",
  "operatingsystem_support": [
        {
        "operatingsystem": "Ubuntu",
        "operatingsystemrelease": [ "12.04", "14.04", "16.04" ]
        }
       ],
  "license": "Apache-2.0",
  "source": "https://github.com/IntroSec/puppet-gnutls",
  "project_page": "https://github.com/IntroSec/puppet-gnutls",
  "issues_url": "https://github.com/IntroSec/puppet-gnutls/issues",
  "tags": ["gnutls","SSL","TLS"],
  "dependencies": [
    {"name":"puppetlabs-stdlib","version_requirement":">= 1.0.0"}
  ],
  "data_provider": null
}

